draughts-0.2.10.dist-info/WHEEL
draughts-0.2.10.dist-info/METADATA
draughts-0.2.10.dist-info/top_level.txt
draughts-0.2.10.dist-info/RECORD
draughts-0.2.10.dist-info/LICENSE
draughts/__init__.cpython-37m-x86_64-linux-gnu.so
draughts/randomizer.cpython-37m-x86_64-linux-gnu.so
draughts/model_decorator.cpython-37m-x86_64-linux-gnu.so
draughts/randomizer.py
draughts/__init__.py
draughts/util.cpython-37m-x86_64-linux-gnu.so
draughts/util.py
draughts/model_decorator.py
draughts/fields/__init__.cpython-37m-x86_64-linux-gnu.so
draughts/fields/complex.py
draughts/fields/multivalued.cpython-37m-x86_64-linux-gnu.so
draughts/fields/__init__.py
draughts/fields/complex.cpython-37m-x86_64-linux-gnu.so
draughts/fields/pattern.cpython-37m-x86_64-linux-gnu.so
draughts/fields/pattern.py
draughts/fields/bases.cpython-37m-x86_64-linux-gnu.so
draughts/fields/basic.cpython-37m-x86_64-linux-gnu.so
draughts/fields/basic.py
draughts/fields/bases.py
draughts/fields/multivalued.py
test/__init__.py
test/test_utils.py
test/test_model.py
test/test_randomizer.py
