Metadata-Version: 2.1
Name: draughts
Version: 0.2.10
Summary: Generates boilerplate for data objects.
Home-page: https://github.com/adam-douglass/draughts/
Author: Adam Douglass
Author-email: douglass@malloc.ca
License: UNKNOWN
Keywords: utility typechecking
Platform: UNKNOWN
Requires-Dist: rstr
Requires-Dist: arrow
Provides-Extra: speedup
Requires-Dist: cython ; extra == 'speedup'
Provides-Extra: test
Requires-Dist: pytest ; extra == 'test'
Requires-Dist: pytest-subtests ; extra == 'test'
